splat_viewer/__init__.py
splat_viewer/benchmark/__init__.py
splat_viewer/benchmark/arguments.py
splat_viewer/benchmark/run.py
splat_viewer/camera/__init__.py
splat_viewer/camera/fov.py
splat_viewer/camera/transforms.py
splat_viewer/camera/visibility.py
splat_viewer/gaussians/__init__.py
splat_viewer/gaussians/data_types.py
splat_viewer/gaussians/loading.py
splat_viewer/gaussians/sh_utils.py
splat_viewer/gaussians/workspace.py
splat_viewer/renderer/__init__.py
splat_viewer/renderer/arguments.py
splat_viewer/renderer/diff_gaussian_rasterization.py
splat_viewer/renderer/taichi_3d_gaussian_splatting.py
splat_viewer/renderer/taichi_splatting.py
splat_viewer/scripts/__init__.py
splat_viewer/scripts/debug_tiles.py
splat_viewer/scripts/export_workspace.py
splat_viewer/scripts/label_foreground.py
splat_viewer/scripts/splat_benchmark.py
splat_viewer/scripts/splat_multi_benchmark.py
splat_viewer/scripts/splat_viewer.py
splat_viewer/viewer/interaction.py
splat_viewer/viewer/keyboard.py
splat_viewer/viewer/mesh.py
splat_viewer/viewer/renderer.py
splat_viewer/viewer/scene_camera.py
splat_viewer/viewer/scene_widget.py
splat_viewer/viewer/settings.py
splat_viewer/viewer/viewer.py
splat_viewer/viewer/interactions/__init__.py
splat_viewer/viewer/interactions/animate.py
splat_viewer/viewer/interactions/fly_control.py
splat_viewer-0.10.0.dist-info/LICENSE
splat_viewer-0.10.0.dist-info/METADATA
splat_viewer-0.10.0.dist-info/WHEEL
splat_viewer-0.10.0.dist-info/entry_points.txt
splat_viewer-0.10.0.dist-info/top_level.txt
splat_viewer-0.10.0.dist-info/RECORD
