Metadata-Version: 2.1
Name: splat-viewer
Version: 0.10.0
Summary: A viewer for gaussian-splatting reconstructions
Maintainer-email: Oliver Batchelor <oliver.batchelor@canterbury.ac.nz>
License: Apache License
Project-URL: Homepage, https://github.com/uc-vision/splat-viewer
Requires-Python: >=3.10
License-File: LICENSE
Requires-Dist: beartype
Requires-Dist: taichi-nightly >=1.8.0
Requires-Dist: taichi-splatting >=0.10.0
Requires-Dist: tqdm
Requires-Dist: tensordict
Requires-Dist: plyfile
Requires-Dist: pyside6
Requires-Dist: natsort
Requires-Dist: opencv-python
Requires-Dist: pyrender
